django_xprez-0.2.36.dist-info/licenses/LICENSE
xprez/__init__.py
xprez/admin.py
xprez/admin_forms.py
xprez/apps.py
xprez/form_fields.py
xprez/permissions.py
xprez/urls.py
xprez/utils.py
xprez/ck_editor/__init__.py
xprez/ck_editor/fields.py
xprez/ck_editor/parse_text.py
xprez/ck_editor/widgets.py
xprez/ck_editor/static/ck_editor/js/ck_editor_widget.js
xprez/ck_editor/static/ck_editor/libs/ck_editor/ckeditor.js
xprez/ck_editor/static/ck_editor/libs/ck_editor/ckeditor.js.map
xprez/ck_editor/static/ck_editor/libs/ck_editor/translations/af.js
xprez/ck_editor/static/ck_editor/libs/ck_editor/translations/ar.js
xprez/ck_editor/static/ck_editor/libs/ck_editor/translations/ast.js
xprez/ck_editor/static/ck_editor/libs/ck_editor/translations/az.js
xprez/ck_editor/static/ck_editor/libs/ck_editor/translations/bg.js
xprez/ck_editor/static/ck_editor/libs/ck_editor/translations/ca.js
xprez/ck_editor/static/ck_editor/libs/ck_editor/translations/cs.js
xprez/ck_editor/static/ck_editor/libs/ck_editor/translations/da.js
xprez/ck_editor/static/ck_editor/libs/ck_editor/translations/de-ch.js
xprez/ck_editor/static/ck_editor/libs/ck_editor/translations/de.js
xprez/ck_editor/static/ck_editor/libs/ck_editor/translations/el.js
xprez/ck_editor/static/ck_editor/libs/ck_editor/translations/en-au.js
xprez/ck_editor/static/ck_editor/libs/ck_editor/translations/en-gb.js
xprez/ck_editor/static/ck_editor/libs/ck_editor/translations/eo.js
xprez/ck_editor/static/ck_editor/libs/ck_editor/translations/es.js
xprez/ck_editor/static/ck_editor/libs/ck_editor/translations/et.js
xprez/ck_editor/static/ck_editor/libs/ck_editor/translations/eu.js
xprez/ck_editor/static/ck_editor/libs/ck_editor/translations/fa.js
xprez/ck_editor/static/ck_editor/libs/ck_editor/translations/fi.js
xprez/ck_editor/static/ck_editor/libs/ck_editor/translations/fr.js
xprez/ck_editor/static/ck_editor/libs/ck_editor/translations/gl.js
xprez/ck_editor/static/ck_editor/libs/ck_editor/translations/gu.js
xprez/ck_editor/static/ck_editor/libs/ck_editor/translations/he.js
django_xprez-0.2.36.dist-info/METADATA
django_xprez-0.2.36.dist-info/WHEEL
django_xprez-0.2.36.dist-info/top_level.txt
django_xprez-0.2.36.dist-info/RECORD
