Metadata-Version: 2.4
Name: django_xprez
Version: 0.2.36
Summary: Django CMS for presentation websites
Home-page: https://github.com/s-cape/django_xprez
Author: Michal Májský, Martin Kappel, Jakub Dolejšek, Michal Tilsch - s-cape.cz & mimatik.com
Author-email: michal.majsky@s-cape.cz
License: Mozilla Public License 2.0 (MPL 2.0)
Classifier: Development Status :: 4 - Beta
Classifier: Environment :: Web Environment
Classifier: Framework :: Django
Classifier: Intended Audience :: Developers
Classifier: License :: OSI Approved :: Mozilla Public License 2.0 (MPL 2.0)
Classifier: Operating System :: OS Independent
Classifier: Programming Language :: Python
License-File: LICENSE
Requires-Dist: html5lib>=1.0b3
Requires-Dist: beautifulsoup4>=4.5.3
Requires-Dist: Pillow>=3.0.0
Requires-Dist: sorl-thumbnail
Requires-Dist: django>=3.1
Dynamic: author
Dynamic: author-email
Dynamic: classifier
Dynamic: description
Dynamic: description-content-type
Dynamic: home-page
Dynamic: license
Dynamic: license-file
Dynamic: requires-dist
Dynamic: summary
